{
    "name": "untitled ed 2",
    "base": "C:\\Users\\Laura Gabriela\\Projects\\EditSheeran\\assets\\christmas card.jpg",
    "overlays": [
        {
            "image": "C:\\Users\\Laura Gabriela\\Projects\\EditSheeran\\assets\\ed_normal.png",
            "x": 300,
            "y": 350,
            "width": 100,
            "height": 100
        },
        {
            "image": "C:\\Users\\Laura Gabriela\\Projects\\EditSheeran\\assets\\ed_normal.png",
            "x": 407,
            "y": 251,
            "width": 100,
            "height": 100
        },
        {
            "image": "C:\\Users\\Laura Gabriela\\Projects\\EditSheeran\\assets\\HEART_EYES.png",
            "x": 168,
            "y": 254,
            "width": 100,
            "height": 100
        },
        {
            "image": "C:\\Users\\Laura Gabriela\\Projects\\EditSheeran\\assets\\open_mouth.png",
            "x": 109,
            "y": 350,
            "width": 100,
            "height": 100
        },
        {
            "image": "C:\\Users\\Laura Gabriela\\Projects\\EditSheeran\\assets\\cowboy_hat.png",
            "x": 411,
            "y": 434,
            "width": 100,
            "height": 100
        }
    ]
}